dgtools/__init__.py
dgtools/assembler.py
dgtools/callbacks.py
dgtools/dgasm.py
dgtools/dgb_archive.py
dgtools/dgbf.py
dgtools/dgform.py
dgtools/dginspect.py
dgtools/dgsim.py
dgtools/dgsust.py
dgtools/dgui.py
dgtools/digirule.py
dgtools/digirule_main_old.py
dgtools/exceptions.py
dgtools/lexer.py
dgtools/makefile_rw.py
dgtools/output_render_html.py
dgtools/css_themes/dgbeos.css
dgtools/css_themes/plain.css
dgtools-1.0.4.data/scripts/dgasm.py
dgtools-1.0.4.data/scripts/dgbf.py
dgtools-1.0.4.data/scripts/dgform.py
dgtools-1.0.4.data/scripts/dginspect.py
dgtools-1.0.4.data/scripts/dgsim.py
dgtools-1.0.4.data/scripts/dgsust.py
dgtools-1.0.4.data/scripts/dgui.py
dgtools-1.0.4.dist-info/LICENSE
dgtools-1.0.4.dist-info/METADATA
dgtools-1.0.4.dist-info/WHEEL
dgtools-1.0.4.dist-info/top_level.txt
dgtools-1.0.4.dist-info/zip-safe
dgtools-1.0.4.dist-info/RECORD
