Metadata-Version: 2.1
Name: dgtools
Version: 1.0.4
Summary: An assembler and simulation toolchain for the Digirule2 series of hardware.
Home-page: https://github.com/aanastasiou/dgtools
Author: Athanasios Anastasiou
Author-email: athanastasiou@gmail.com
License: Apache2.0
Platform: UNKNOWN
Classifier: Development Status :: 4 - Beta
Classifier: Environment :: Console
Classifier: Intended Audience :: Developers
Classifier: Intended Audience :: Education
Classifier: Intended Audience :: Information Technology
Classifier: Natural Language :: English
Classifier: Programming Language :: Python
Classifier: Topic :: Software Development :: Assemblers
Classifier: Topic :: Software Development :: Code Generators
Classifier: Topic :: Software Development :: Compilers
Classifier: Topic :: Utilities
Classifier: License :: OSI Approved :: Apache Software License
Requires-Python: >=3.6
Requires-Dist: click
Requires-Dist: pyparsing
Requires-Dist: urwid
Requires-Dist: pygments
Requires-Dist: intelhex
